Singularity_Server-0.1.2.data/scripts/server_run
server/__init__.py
server/server.py
server/common/__init__.py
server/common/decos.py
server/common/descrptrs.py
server/common/errors.py
server/common/metaclasses.py
server/common/utils.py
server/common/variables.py
server/logs/__init__.py
server/logs/config_client_log.py
server/logs/config_server_log.py
server/server_file/__init__.py
server/server_file/add_user.py
server/server_file/config_window.py
server/server_file/core.py
server/server_file/main_window.py
server/server_file/remove_user.py
server/server_file/server_database.py
server/server_file/stat_window.py
Singularity_Server-0.1.2.dist-info/METADATA
Singularity_Server-0.1.2.dist-info/WHEEL
Singularity_Server-0.1.2.dist-info/top_level.txt
Singularity_Server-0.1.2.dist-info/RECORD
