Metadata-Version: 2.1
Name: Singularity-Server
Version: 0.1.2
Summary: Singularity Server
Home-page: UNKNOWN
Author: PanovaM
Author-email: ri5@mail.ru
License: UNKNOWN
Platform: UNKNOWN
Requires-Dist: PyQt5
Requires-Dist: sqlalchemy
Requires-Dist: pycryptodome
Requires-Dist: pycryptodomex
